bytecorefast/__init__.py
bytecorefast/accumulator.py
bytecorefast/bit.py
bytecorefast/byte.py
bytecorefast/byte_register.py
bytecorefast/constant_register.py
bytecorefast/control_unit.py
bytecorefast/control_unit_state.py
bytecorefast/cpu.py
bytecorefast/emulator.py
bytecorefast/fast_emulator.c
bytecorefast/fast_emulator.cp311-win_amd64.pyd
bytecorefast/fast_emulator.pyi
bytecorefast/memory.py
bytecorefast/memory_bytes_builder.py
bytecorefast/opcode.py
bytecorefast/proxy_register.py
bytecorefast/py.typed
bytecorefast/register.py
bytecorefast/replay_register.py
bytecorefast/state.py
bytecorefast-1.0.2.dist-info/LICENSE
bytecorefast-1.0.2.dist-info/METADATA
bytecorefast-1.0.2.dist-info/WHEEL
bytecorefast-1.0.2.dist-info/top_level.txt
bytecorefast-1.0.2.dist-info/RECORD
