Metadata-Version: 2.1
Name: bytecorefast
Version: 1.0.2
Summary: A high-performance, 8-bit CPU emulator, designed as a drop-in replacement for ByteCore, offering enhanced speed while maintaining full compatibility with the original ByteCore interfaces.
Author-email: Joakim Winum Lien <joakim@winum.xyz>
Project-URL: Homepage, https://github.com/joakimwinum/bytecorefast
Project-URL: Bug Tracker, https://github.com/joakimwinum/bytecorefast/issues
Classifier: Programming Language :: Python :: 3
Classifier: License :: OSI Approved :: MIT License
Classifier: Operating System :: OS Independent
Requires-Python: >=3.11
License-File: LICENSE
Requires-Dist: bytecore ==1.1.2
Provides-Extra: dev
Requires-Dist: mypy ; extra == 'dev'
Requires-Dist: types-setuptools ; extra == 'dev'
Requires-Dist: pytest ; extra == 'dev'
